{
  "formatVersion": 1,
  "database": {
    "version": 5,
    "identityHash": "36e51ade837763f3dfe27e221d3e0c7a",
    "entities": [
      {
        "tableName": "text_notes",
        "createSql": "CREATE TABLE IF NOT EXISTS `${TABLE_NAME}` (`content` TEXT NOT NULL, `uid` INTEGER PRIMARY KEY AUTOINCREMENT NOT NULL, `lastUpdated` INTEGER NOT NULL, `created` INTEGER NOT NULL)",
        "fields": [
          {
            "fieldPath": "content",
            "columnName": "content",
            "affinity": "TEXT",
            "notNull": true
          },
          {
            "fieldPath": "uid",
            "columnName": "uid",
            "affinity": "INTEGER",
            "notNull": true
          },
          {
            "fieldPath": "lastUpdated",
            "columnName": "lastUpdated",
            "affinity": "INTEGER",
            "notNull": true
          },
          {
            "fieldPath": "created",
            "columnName": "created",
            "affinity": "INTEGER",
            "notNull": true
          }
        ],
        "primaryKey": {
          "autoGenerate": true,
          "columnNames": [
            "uid"
          ]
        },
        "indices": [],
        "foreignKeys": []
      },
      {
        "tableName": "image_notes",
        "createSql": "CREATE TABLE IF NOT EXISTS `${TABLE_NAME}` (`contentUri` TEXT NOT NULL, `uid` INTEGER PRIMARY KEY AUTOINCREMENT NOT NULL, `lastUpdated` INTEGER NOT NULL, `created` INTEGER NOT NULL)",
        "fields": [
          {
            "fieldPath": "contentUri",
            "columnName": "contentUri",
            "affinity": "TEXT",
            "notNull": true
          },
          {
            "fieldPath": "uid",
            "columnName": "uid",
            "affinity": "INTEGER",
            "notNull": true
          },
          {
            "fieldPath": "lastUpdated",
            "columnName": "lastUpdated",
            "affinity": "INTEGER",
            "notNull": true
          },
          {
            "fieldPath": "created",
            "columnName": "created",
            "affinity": "INTEGER",
            "notNull": true
          }
        ],
        "primaryKey": {
          "autoGenerate": true,
          "columnNames": [
            "uid"
          ]
        },
        "indices": [],
        "foreignKeys": []
      },
      {
        "tableName": "journals",
        "createSql": "CREATE TABLE IF NOT EXISTS `${TABLE_NAME}` (`id` INTEGER PRIMARY KEY AUTOINCREMENT NOT NULL, `title` TEXT NOT NULL, `description` TEXT NOT NULL, `created` INTEGER NOT NULL, `lastUpdated` INTEGER NOT NULL)",
        "fields": [
          {
            "fieldPath": "id",
            "columnName": "id",
            "affinity": "INTEGER",
            "notNull": true
          },
          {
            "fieldPath": "title",
            "columnName": "title",
            "affinity": "TEXT",
            "notNull": true
          },
          {
            "fieldPath": "description",
            "columnName": "description",
            "affinity": "TEXT",
            "notNull": true
          },
          {
            "fieldPath": "created",
            "columnName": "created",
            "affinity": "INTEGER",
            "notNull": true
          },
          {
            "fieldPath": "lastUpdated",
            "columnName": "lastUpdated",
            "affinity": "INTEGER",
            "notNull": true
          }
        ],
        "primaryKey": {
          "autoGenerate": true,
          "columnNames": [
            "id"
          ]
        },
        "indices": [],
        "foreignKeys": []
      },
      {
        "tableName": "journal_notes",
        "createSql": "CREATE TABLE IF NOT EXISTS `${TABLE_NAME}` (`id` INTEGER NOT NULL, `uid` INTEGER NOT NULL, PRIMARY KEY(`id`, `uid`))",
        "fields": [
          {
            "fieldPath": "journalId",
            "columnName": "id",
            "affinity": "INTEGER",
            "notNull": true
          },
          {
            "fieldPath": "noteId",
            "columnName": "uid",
            "affinity": "INTEGER",
            "notNull": true
          }
        ],
        "primaryKey": {
          "autoGenerate": false,
          "columnNames": [
            "id",
            "uid"
          ]
        },
        "indices": [
          {
            "name": "index_journal_notes_id",
            "unique": false,
            "columnNames": [
              "id"
            ],
            "orders": [],
            "createSql": "CREATE INDEX IF NOT EXISTS `index_journal_notes_id` ON `${TABLE_NAME}` (`id`)"
          },
          {
            "name": "index_journal_notes_uid",
            "unique": false,
            "columnNames": [
              "uid"
            ],
            "orders": [],
            "createSql": "CREATE INDEX IF NOT EXISTS `index_journal_notes_uid` ON `${TABLE_NAME}` (`uid`)"
          }
        ],
        "foreignKeys": []
      },
      {
        "tableName": "location_logs",
        "createSql": "CREATE TABLE IF NOT EXISTS `${TABLE_NAME}` (`user_id` TEXT NOT NULL, `device_id` TEXT NOT NULL, `timestamp` INTEGER NOT NULL, `confidence` REAL NOT NULL, `is_genuine` INTEGER NOT NULL, `latitude` REAL NOT NULL, `longitude` REAL NOT NULL, `altitude` REAL NOT NULL, PRIMARY KEY(`user_id`, `device_id`, `timestamp`))",
        "fields": [
          {
            "fieldPath": "userId",
            "columnName": "user_id",
            "affinity": "TEXT",
            "notNull": true
          },
          {
            "fieldPath": "deviceId",
            "columnName": "device_id",
            "affinity": "TEXT",
            "notNull": true
          },
          {
            "fieldPath": "timestamp",
            "columnName": "timestamp",
            "affinity": "INTEGER",
            "notNull": true
          },
          {
            "fieldPath": "confidence",
            "columnName": "confidence",
            "affinity": "REAL",
            "notNull": true
          },
          {
            "fieldPath": "isGenuine",
            "columnName": "is_genuine",
            "affinity": "INTEGER",
            "notNull": true
          },
          {
            "fieldPath": "location.latitude",
            "columnName": "latitude",
            "affinity": "REAL",
            "notNull": true
          },
          {
            "fieldPath": "location.longitude",
            "columnName": "longitude",
            "affinity": "REAL",
            "notNull": true
          },
          {
            "fieldPath": "location.altitude",
            "columnName": "altitude",
            "affinity": "REAL",
            "notNull": true
          }
        ],
        "primaryKey": {
          "autoGenerate": false,
          "columnNames": [
            "user_id",
            "device_id",
            "timestamp"
          ]
        },
        "indices": [],
        "foreignKeys": []
      },
      {
        "tableName": "user_devices",
        "createSql": "CREATE TABLE IF NOT EXISTS `${TABLE_NAME}` (`uid` TEXT NOT NULL, `user_id` TEXT NOT NULL, `label` TEXT NOT NULL, `operating_system` TEXT NOT NULL, `version` TEXT NOT NULL, `model` TEXT NOT NULL, `type` TEXT NOT NULL, `added` INTEGER NOT NULL, PRIMARY KEY(`uid`))",
        "fields": [
          {
            "fieldPath": "uid",
            "columnName": "uid",
            "affinity": "TEXT",
            "notNull": true
          },
          {
            "fieldPath": "userId",
            "columnName": "user_id",
            "affinity": "TEXT",
            "notNull": true
          },
          {
            "fieldPath": "label",
            "columnName": "label",
            "affinity": "TEXT",
            "notNull": true
          },
          {
            "fieldPath": "operatingSystem",
            "columnName": "operating_system",
            "affinity": "TEXT",
            "notNull": true
          },
          {
            "fieldPath": "version",
            "columnName": "version",
            "affinity": "TEXT",
            "notNull": true
          },
          {
            "fieldPath": "model",
            "columnName": "model",
            "affinity": "TEXT",
            "notNull": true
          },
          {
            "fieldPath": "type",
            "columnName": "type",
            "affinity": "TEXT",
            "notNull": true
          },
          {
            "fieldPath": "added",
            "columnName": "added",
            "affinity": "INTEGER",
            "notNull": true
          }
        ],
        "primaryKey": {
          "autoGenerate": false,
          "columnNames": [
            "uid"
          ]
        },
        "indices": [],
        "foreignKeys": []
      },
      {
        "tableName": "media_images",
        "createSql": "CREATE TABLE IF NOT EXISTS `${TABLE_NAME}` (`id` INTEGER PRIMARY KEY AUTOINCREMENT NOT NULL, `uri` TEXT NOT NULL, `addedTimestamp` INTEGER NOT NULL, `lastUpdated` INTEGER NOT NULL)",
        "fields": [
          {
            "fieldPath": "id",
            "columnName": "id",
            "affinity": "INTEGER",
            "notNull": true
          },
          {
            "fieldPath": "uri",
            "columnName": "uri",
            "affinity": "TEXT",
            "notNull": true
          },
          {
            "fieldPath": "addedTimestamp",
            "columnName": "addedTimestamp",
            "affinity": "INTEGER",
            "notNull": true
          },
          {
            "fieldPath": "lastUpdated",
            "columnName": "lastUpdated",
            "affinity": "INTEGER",
            "notNull": true
          }
        ],
        "primaryKey": {
          "autoGenerate": true,
          "columnNames": [
            "id"
          ]
        },
        "indices": [],
        "foreignKeys": []
      },
      {
        "tableName": "rewinds",
        "createSql": "CREATE TABLE IF NOT EXISTS `${TABLE_NAME}` (`uid` TEXT NOT NULL, PRIMARY KEY(`uid`))",
        "fields": [
          {
            "fieldPath": "uid",
            "columnName": "uid",
            "affinity": "TEXT",
            "notNull": true
          }
        ],
        "primaryKey": {
          "autoGenerate": false,
          "columnNames": [
            "uid"
          ]
        },
        "indices": [],
        "foreignKeys": []
      }
    ],
    "views": [],
    "setupQueries": [
      "CREATE TABLE IF NOT EXISTS room_master_table (id INTEGER PRIMARY KEY,identity_hash TEXT)",
      "INSERT OR REPLACE INTO room_master_table (id,identity_hash) VALUES(42, '36e51ade837763f3dfe27e221d3e0c7a')"
    ]
  }
}